data/__init__.py
data/data_ingestion/__init__.py
data/data_ingestion/interface.py
data/data_ingestion/setup_logging.py
data/data_ingestion/storage_handler.py
data/data_ingestion/tes.py
data/data_ingestion/handlers/__init__.py
data/data_ingestion/handlers/conditions.py
data/data_ingestion/handlers/huggingface_handler.py
data/data_ingestion/handlers/kaggle_handler.py
data/data_ingestion/handlers/local_handler.py
data/data_ingestion/handlers/openml_handler.py
data/data_ingestion/handlers/s3_handler.py
data/data_ingestion/handlers/utils.py
data/data_ingestion/models/__init__.py
data/data_ingestion/models/metadata.py
data/data_ingestion/models/requests.py
data/data_restructure/__init__.py
data/data_restructure/file_convert.py
data/data_restructure/par_loading.py
data/data_restructure/restructure.py
data/data_restructure/restructurers.py
data/data_restructure/run_converter.py
data/data_restructure/run_restructure.py
data/data_restructure/run_segmentation_template.py
data/data_restructure/run_text_generation.py
data/data_restructure/test_convert.py
data/data_restructure/utils.py
data/data_validation/__init__.py
data/data_validation/config.py
data/data_validation/run_validator.py
data/data_validation/structures.py
data/data_validation/utils.py
data/data_validation/validation.py
data/data_validation/validators.py
data/sdk/__init__.py
data/sdk/datasets_object.py
data/sdk/download_sdk.py
data/sdk/run_download_sdk.py
ryn_data-0.2.19.dist-info/METADATA
ryn_data-0.2.19.dist-info/WHEEL
ryn_data-0.2.19.dist-info/top_level.txt
ryn_data-0.2.19.dist-info/RECORD
