Metadata-Version: 2.4
Name: ryn-data
Version: 0.2.19
Summary: SDK for data ingestion and platform utilities.
Requires-Python: >=3.8
Requires-Dist: pydantic
Requires-Dist: boto3
Requires-Dist: pandas
Requires-Dist: datasets
Requires-Dist: openml
Requires-Dist: kagglehub
Requires-Dist: fastapi
Requires-Dist: opencv-python
Requires-Dist: opencv-python-headless
Requires-Dist: polars
Requires-Dist: pydicom
Requires-Dist: nibabel
Requires-Dist: librosa
Requires-Dist: pyspark
Requires-Dist: elasticsearch<9
Requires-Dist: ecs-logging
Requires-Dist: clearml
Requires-Dist: aipmodel==0.2.28
Dynamic: description
Dynamic: description-content-type
Dynamic: requires-dist
Dynamic: requires-python
Dynamic: summary
